{
    "items": [
      {
        "itemID": "0001",
        "itemName": "Milk",
        "nfcTagID": "nfc0001",
        "pDate": "2024-03-01",
        "xDate": "2024-03-15",
        "inDate": "2024-03-02",
        "itemInfo": "1L Organic Milk",
        "status": "fresh",
        "category": "Dairy",
        "quantity": 1,
        "unit": "Liter"
      },
      {
        "itemID": "0002",
        "itemName": "Eggs",
        "nfcTagID": "nfc0002",
        "pDate": "2024-03-01",
        "xDate": "2024-03-22",
        "inDate": "2024-03-02",
        "itemInfo": "12 Free-range Eggs",
        "status": "fresh",
        "category": "Poultry",
        "quantity": 12,
        "unit": "Pieces"
      },
      {
        "itemID": "0003",
        "itemName": "Cheddar Cheese",
        "nfcTagID": "nfc0003",
        "pDate": "2024-02-25",
        "xDate": "2024-05-25",
        "inDate": "2024-03-02",
        "itemInfo": "Matured Cheddar, 250g",
        "status": "fresh",
        "category": "Dairy",
        "quantity": 250,
        "unit": "Grams"
      },
      {
        "itemID": "0004",
        "itemName": "Apples",
        "nfcTagID": "nfc0004",
        "pDate": "2024-03-01",
        "xDate": "2024-03-12",
        "inDate": "2024-03-02",
        "itemInfo": "Green Apples, Pack of 6",
        "status": "fresh",
        "category": "Fruits",
        "quantity": 6,
        "unit": "Pieces"
      },
      {
        "itemID": "0005",
        "itemName": "Orange Juice",
        "nfcTagID": "nfc0005",
        "pDate": "2024-03-01",
        "xDate": "2024-03-10",
        "inDate": "2024-03-02",
        "itemInfo": "Freshly Squeezed Orange Juice",
        "status": "fresh",
        "category": "Beverages",
        "quantity": 1,
        "unit": "Liter"
      },
      {
        "itemID": "0006",
        "itemName": "Whole Wheat Bread",
        "nfcTagID": "nfc0006",
        "pDate": "2024-03-01",
        "xDate": "2024-03-07",
        "inDate": "2024-03-02",
        "itemInfo": "Freshly Baked Whole Wheat Bread",
        "status": "fresh",
        "category": "Bakery",
        "quantity": 1,
        "unit": "Loaf"
      },
      {
        "itemID": "0007",
        "itemName": "Salmon Fillets",
        "nfcTagID": "nfc0007",
        "pDate": "2024-02-28",
        "xDate": "2024-03-05",
        "inDate": "2024-03-02",
        "itemInfo": "Fresh Atlantic Salmon Fillets",
        "status": "fresh",
        "category": "Seafood",
        "quantity": 4,
        "unit": "Pieces"
      },
      {
        "itemID": "0008",
        "itemName": "Spinach",
        "nfcTagID": "nfc0008",
        "pDate": "2024-02-29",
        "xDate": "2024-03-07",
        "inDate": "2024-03-02",
        "itemInfo": "Organic Baby Spinach",
        "status": "fresh",
        "category": "Produce",
        "quantity": 200,
        "unit": "Grams"
      },
      {
        "itemID": "0009",
        "itemName": "Tomatoes",
        "nfcTagID": "nfc0009",
        "pDate": "2024-02-29",
        "xDate": "2024-03-05",
        "inDate": "2024-03-02",
        "itemInfo": "Vine-Ripened Tomatoes, Pack of 6",
        "status": "fresh",
        "category": "Produce",
        "quantity": 6,
        "unit": "Pieces"
    },
    {
        "itemID": "0010",
        "itemName": "Ground Beef",
        "nfcTagID": "nfc0010",
        "pDate": "2024-02-28",
        "xDate": "2024-03-04",
        "inDate": "2024-03-02",
        "itemInfo": "Lean Ground Beef, 500g",
        "status": "fresh",
        "category": "Meat",
        "quantity": 500,
        "unit": "Grams"
    },
    {
        "itemID": "0011",
        "itemName": "Bananas",
        "nfcTagID": "nfc0011",
        "pDate": "2024-03-01",
        "xDate": "2024-03-07",
        "inDate": "2024-03-02",
        "itemInfo": "Ripe Bananas, Bunch of 6",
        "status": "fresh",
        "category": "Fruits",
        "quantity": 6,
        "unit": "Pieces"
    },
    {
        "itemID": "0012",
        "itemName": "Pasta",
        "nfcTagID": "nfc0012",
        "pDate": "2024-02-29",
        "xDate": "2025-02-28",
        "inDate": "2024-03-02",
        "itemInfo": "Whole Wheat Spaghetti, 500g",
        "status": "fresh",
        "category": "Pantry",
        "quantity": 500,
        "unit": "Grams"
    },
    {
        "itemID": "0013",
        "itemName": "Yogurt",
        "nfcTagID": "nfc0013",
        "pDate": "2024-03-01",
        "xDate": "2024-03-10",
        "inDate": "2024-03-02",
        "itemInfo": "Greek Yogurt, 1kg",
        "status": "fresh",
        "category": "Dairy",
        "quantity": 1000,
        "unit": "Grams"
    },
    {
        "itemID": "0014",
        "itemName": "Potatoes",
        "nfcTagID": "nfc0014",
        "pDate": "2024-02-29",
        "xDate": "2024-03-15",
        "inDate": "2024-03-02",
        "itemInfo": "Russet Potatoes, Bag of 2kg",
        "status": "fresh",
        "category": "Produce",
        "quantity": 2000,
        "unit": "Grams"
    },
    {
        "itemID": "0015",
        "itemName": "Almond Milk",
        "nfcTagID": "nfc0015",
        "pDate": "2024-02-28",
        "xDate": "2024-03-14",
        "inDate": "2024-03-02",
        "itemInfo": "Unsweetened Almond Milk, 1L",
        "status": "fresh",
        "category": "Dairy",
        "quantity": 1,
        "unit": "Liter"
    },
    {
        "itemID": "0016",
        "itemName": "Chicken Breast",
        "nfcTagID": "nfc0016",
        "pDate": "2024-02-29",
        "xDate": "2024-03-07",
        "inDate": "2024-03-02",
        "itemInfo": "Skinless Chicken Breast, 500g",
        "status": "fresh",
        "category": "Poultry",
        "quantity": 500,
        "unit": "Grams"
    },
    {
        "itemID": "0017",
        "itemName": "Rice",
        "nfcTagID": "nfc0017",
        "pDate": "2024-02-28",
        "xDate": "2025-02-28",
        "inDate": "2024-03-02",
        "itemInfo": "Basmati Rice, 2kg",
        "status": "fresh",
        "category": "Pantry",
        "quantity": 2000,
        "unit": "Grams"
    },
    {
        "itemID": "0018",
        "itemName": "Broccoli",
        "nfcTagID": "nfc0018",
        "pDate": "2024-03-01",
        "xDate": "2024-03-07",
        "inDate": "2024-03-02",
        "itemInfo": "Fresh Broccoli Florets, 500g",
        "status": "fresh",
        "category": "Produce",
        "quantity": 500,
        "unit": "Grams"
    },
    {
        "itemID": "0019",
        "itemName": "Lemon",
        "nfcTagID": "nfc0019",
        "pDate": "2024-02-29",
        "xDate": "2024-03-07",
        "inDate": "2024-03-02",
        "itemInfo": "Fresh Lemons, Pack of 4",
        "status": "fresh",
        "category": "Produce",
        "quantity": 4,
        "unit": "Pieces"
    },
    {
        "itemID": "0020",
        "itemName": "Black Beans",
        "nfcTagID": "nfc0020",
        "pDate": "2024-02-28",
        "xDate": "2024-02-28",
        "inDate": "2024-03-02",
        "itemInfo": "Dried Black Beans, 500g",
        "status": "dry",
        "category": "Pantry",
        "quantity": 500,
        "unit": "Grams"
    } 
    ]
  }
  